{
  "publicPath": "/",
  "js": [
    "js/runtime.ab91ed04.js",
    "js/i18n.df766328.js",
    "js/i18n-langs.i18n-completenesses.81a2efdc.js",
    "js/npm-rxjs.ca264902.js",
    "js/npm-emotion.c67cac27.js",
    "js/npm-react.eb6ad3dd.js",
    "js/npm-jotai.697b33a1.js",
    "js/npm-blocksuite.6196e346.js",
    "js/vendor.5fed4bf9.js",
    "js/index.77b60b97.js"
  ],
  "css": [
    "styles.edebbfea.css",
    "vendor.1f328f6f.css"
  ],
  "gitHash": "9ccb0e1",
  "description": "There can be more than Notion and Miro. AFFiNE is a next-gen knowledge base that brings planning, sorting and creating all together."
}